ocrd_physical_import/__init__.py
ocrd_physical_import/scan.ui
ocrd_physical_import/view.py
ocrd_physical_import/scandriver/__init__.py
browse_ocrd_physical_import-0.2.2.dist-info/LICENSE
browse_ocrd_physical_import-0.2.2.dist-info/METADATA
browse_ocrd_physical_import-0.2.2.dist-info/WHEEL
browse_ocrd_physical_import-0.2.2.dist-info/entry_points.txt
browse_ocrd_physical_import-0.2.2.dist-info/top_level.txt
browse_ocrd_physical_import-0.2.2.dist-info/RECORD
